LICENSE
MANIFEST.in
README.md
setup.py
dznkyciabp/__init__.py
dznkyciabp/api_helper.py
dznkyciabp/configuration.py
dznkyciabp/decorators.py
dznkyciabp/dznkyciabp_client.py
dznkyciabp.egg-info/PKG-INFO
dznkyciabp.egg-info/SOURCES.txt
dznkyciabp.egg-info/dependency_links.txt
dznkyciabp.egg-info/requires.txt
dznkyciabp.egg-info/top_level.txt
dznkyciabp/controllers/__init__.py
dznkyciabp/controllers/api_controller.py
dznkyciabp/controllers/base_controller.py
dznkyciabp/exceptions/__init__.py
dznkyciabp/exceptions/api_exception.py
dznkyciabp/http/__init__.py
dznkyciabp/http/http_call_back.py
dznkyciabp/http/http_client.py
dznkyciabp/http/http_context.py
dznkyciabp/http/http_method_enum.py
dznkyciabp/http/http_request.py
dznkyciabp/http/http_response.py
dznkyciabp/http/requests_client.py
dznkyciabp/http/auth/__init__.py
dznkyciabp/http/auth/basic_auth.py
dznkyciabp/models/__init__.py
dznkyciabp/models/suite_code_enum.py
tests/__init__.py
tests/http_response_catcher.py
tests/test_helper.py
tests/controllers/__init__.py
tests/controllers/controller_test_base.py
tests/controllers/test_api_controller.py